termenu/__init__.py
termenu/menus/leftright.py
termenu/menus/options.py
termenu/menus/plain.py
termenu/utils/ascii.py
termenu/utils/exceptions.py
python_termenu-0.1.4.dist-info/LICENSE.txt
python_termenu-0.1.4.dist-info/METADATA
python_termenu-0.1.4.dist-info/WHEEL
python_termenu-0.1.4.dist-info/top_level.txt
python_termenu-0.1.4.dist-info/RECORD
